hexalog/__init__.py
hexalog/adapters/__init__.py
hexalog/adapters/cli_logger.py
hexalog/adapters/logger_for_tests.py
hexalog/adapters/struct_logger.py
hexalog/ports.py
hexalog-0.6.0.dist-info/METADATA
hexalog-0.6.0.dist-info/WHEEL
hexalog-0.6.0.dist-info/RECORD
