Metadata-Version: 2.1
Name: HexaLog
Version: 0.6.0
Summary: HexaLog is a logging port and set of opinionated adapters meant to simplify using a logger in a hexagonal architecture.
Author: ericcbonet
Author-email: ericcbonet@gmail.com
Requires-Python: >=3.10,<4.0
Classifier: Programming Language :: Python :: 3
Classifier: Programming Language :: Python :: 3.10
Classifier: Programming Language :: Python :: 3.11
Classifier: Programming Language :: Python :: 3.12
Requires-Dist: structlog (==23.2.0)
